{"status":"ready","originalFilePath":"https://storage.googleapis.com/muxdemofiles/mux.mp4","provider":"vercel-blob","providerMetadata":{"vercel-blob":{"key":"videos/mux.mp4","url":"https://p2kzwwhnykpzlhrx.public.blob.vercel-storage.com/videos/mux-BI9p2oskfxfQZU79gqedlQRhwOEGXR.mp4","contentType":"video/mp4"}},"createdAt":1741207347549,"updatedAt":1741207365063,"sources":[{"src":"https://p2kzwwhnykpzlhrx.public.blob.vercel-storage.com/videos/mux-BI9p2oskfxfQZU79gqedlQRhwOEGXR.mp4","type":"video/mp4"}]}